ytdlphelper/__init__.py
ytdlphelper/cli.py
yt_dlp_helper-0.1.1.dist-info/METADATA
yt_dlp_helper-0.1.1.dist-info/WHEEL
yt_dlp_helper-0.1.1.dist-info/entry_points.txt
yt_dlp_helper-0.1.1.dist-info/licenses/LICENSE
yt_dlp_helper-0.1.1.dist-info/RECORD
