Metadata-Version: 2.4
Name: yt-dlp-helper
Version: 0.1.1
Summary: A beautiful command-line wrapper for yt-dlp with a rich interface
Project-URL: Homepage, https://github.com/igutekunst/yt-dlp-helper
Project-URL: Repository, https://github.com/igutekunst/yt-dlp-helper
Author: Isaac Gutekunst
License-Expression: MIT
License-File: LICENSE
Classifier: License :: OSI Approved :: MIT License
Classifier: Operating System :: OS Independent
Classifier: Programming Language :: Python :: 3
Requires-Python: >=3.6
Requires-Dist: requests
Requires-Dist: rich
Requires-Dist: typer
Requires-Dist: yt-dlp
